mdc_tool/__init__.py
mdc_tool/launcher.py
mdc_tool/main.py
mdc_rackauskas-0.4.dist-info/METADATA
mdc_rackauskas-0.4.dist-info/WHEEL
mdc_rackauskas-0.4.dist-info/entry_points.txt
mdc_rackauskas-0.4.dist-info/top_level.txt
mdc_rackauskas-0.4.dist-info/RECORD
