Metadata-Version: 2.4
Name: mdc-rackauskas
Version: 0.4
Summary: Minecraft server downloader ir launcher
Author: Tavo vardas
Classifier: Programming Language :: Python :: 3
Classifier: Operating System :: OS Independent
Requires-Python: >=3.6
Requires-Dist: colorama
Dynamic: author
Dynamic: classifier
Dynamic: description
Dynamic: description-content-type
Dynamic: requires-dist
Dynamic: requires-python
Dynamic: summary
